rmount/__init__.py
rmount/config.py
rmount/main.py
rmount/rclone
rmount/server.py
rmount/utils.py
rmount-0.0.7.dist-info/LICENSE
rmount-0.0.7.dist-info/METADATA
rmount-0.0.7.dist-info/WHEEL
rmount-0.0.7.dist-info/top_level.txt
rmount-0.0.7.dist-info/RECORD
