Metadata-Version: 2.1
Name: rmount
Version: 0.0.7
Summary: A robust file-system mount to a remote storage.
Home-page: https://github.com/fostiropoulos/rmount
Author: Iordanis Fostiropoulos
Author-email: mail@iordanis.me
Requires-Python: >=3.10
License-File: LICENSE
Provides-Extra: dev
Requires-Dist: mypy >=1.2.0 ; extra == 'dev'
Requires-Dist: pytest >=7.3.0 ; extra == 'dev'
Requires-Dist: black ==23.3.0 ; extra == 'dev'
Requires-Dist: flake8 >=6.0.0 ; extra == 'dev'
Requires-Dist: pylint >=2.17.2 ; extra == 'dev'
Requires-Dist: mock >=5.0.2 ; extra == 'dev'
Requires-Dist: docker >=6.1.3 ; extra == 'dev'
Requires-Dist: pydoclint >=0.1.0 ; extra == 'dev'
Requires-Dist: paramiko >=3.2.0 ; extra == 'dev'
Provides-Extra: server
Requires-Dist: docker >=6.1.3 ; extra == 'server'
